django_binaryfield-0.4.0.dist-info/METADATA
django_binaryfield-0.4.0.dist-info/top_level.txt
django_binaryfield-0.4.0.dist-info/pydist.json
django_binaryfield-0.4.0.dist-info/RECORD
django_binaryfield-0.4.0.dist-info/WHEEL
django_binaryfield-0.4.0.dist-info/DESCRIPTION.rst
binaryfield/__init__.py
binaryfield/models.py
binaryfield/hacks.py
binaryfield/views.py
