Metadata-Version: 2.0
Name: django-binaryfield
Version: 0.4.0
Summary: a generic app to provide a way to handle database binary data in django
Home-page: https://bitbucket.org/slafs/django-binaryfield/
Author: Slawek Ehlert
Author-email: slafs@op.pl
License: BSD
Platform: UNKNOWN
Classifier: Environment :: Web Environment
Classifier: Framework :: Django
Classifier: Intended Audience :: Developers
Classifier: License :: OSI Approved :: BSD License
Classifier: Operating System :: OS Independent
Classifier: Programming Language :: Python
Classifier: Programming Language :: Python :: 2.6
Classifier: Programming Language :: Python :: 2.7
Classifier: Programming Language :: Python :: 3
Classifier: Programming Language :: Python :: 3.2
Classifier: Programming Language :: Python :: 3.3
Classifier: Topic :: Utilities
